#![allow(non_camel_case_types, unused, non_upper_case_globals, non_snake_case)]
// include!(concat!(env!("OUT_DIR"), "/_classfile_constants.rs"));

/* automatically generated by rust-bindgen 0.70.1 */

pub const JVM_CLASSFILE_MAJOR_VERSION: u16 = 65;
pub const JVM_CLASSFILE_MINOR_VERSION: u16 = 0;
pub const JVM_ACC_PUBLIC_BIT: u16 = 0;
pub const JVM_ACC_PRIVATE_BIT: u16 = 1;
pub const JVM_ACC_PROTECTED_BIT: u16 = 2;
pub const JVM_ACC_STATIC_BIT: u16 = 3;
pub const JVM_ACC_FINAL_BIT: u16 = 4;
pub const JVM_ACC_SYNCHRONIZED_BIT: u16 = 5;
pub const JVM_ACC_SUPER_BIT: u16 = 5;
pub const JVM_ACC_VOLATILE_BIT: u16 = 6;
pub const JVM_ACC_BRIDGE_BIT: u16 = 6;
pub const JVM_ACC_TRANSIENT_BIT: u16 = 7;
pub const JVM_ACC_VARARGS_BIT: u16 = 7;
pub const JVM_ACC_NATIVE_BIT: u16 = 8;
pub const JVM_ACC_INTERFACE_BIT: u16 = 9;
pub const JVM_ACC_ABSTRACT_BIT: u16 = 10;
pub const JVM_ACC_STRICT_BIT: u16 = 11;
pub const JVM_ACC_SYNTHETIC_BIT: u16 = 12;
pub const JVM_ACC_ANNOTATION_BIT: u16 = 13;
pub const JVM_ACC_ENUM_BIT: u32 = 14;
pub const JVM_ACC_PUBLIC: u16 = 1;
pub const JVM_ACC_PRIVATE: u16 = 2;
pub const JVM_ACC_PROTECTED: u16 = 4;
pub const JVM_ACC_STATIC: u16 = 8;
pub const JVM_ACC_FINAL: u16 = 16;
pub const JVM_ACC_SYNCHRONIZED: u16 = 32;
pub const JVM_ACC_SUPER: u16 = 32;
pub const JVM_ACC_VOLATILE: u16 = 64;
pub const JVM_ACC_BRIDGE: u16 = 64;
pub const JVM_ACC_TRANSIENT: u16 = 128;
pub const JVM_ACC_VARARGS: u16 = 128;
pub const JVM_ACC_NATIVE: u16 = 256;
pub const JVM_ACC_INTERFACE: u16 = 512;
pub const JVM_ACC_ABSTRACT: u16 = 1024;
pub const JVM_ACC_STRICT: u16 = 2048;
pub const JVM_ACC_SYNTHETIC: u16 = 4096;
pub const JVM_ACC_ANNOTATION: u16 = 8192;
pub const JVM_ACC_ENUM: u16 = 16384;
pub const JVM_ACC_MODULE: u16 = 32768;

pub const JVM_T_BOOLEAN: u8 = 4;
pub const JVM_T_CHAR: u8 = 5;
pub const JVM_T_FLOAT: u8 = 6;
pub const JVM_T_DOUBLE: u8 = 7;
pub const JVM_T_BYTE: u8 = 8;
pub const JVM_T_SHORT: u8 = 9;
pub const JVM_T_INT: u8 = 10;
pub const JVM_T_LONG: u8 = 11;

pub const JVM_CONSTANT_Utf8: u8 = 1;
pub const JVM_CONSTANT_Unicode: u8 = 2;
pub const JVM_CONSTANT_Integer: u8 = 3;
pub const JVM_CONSTANT_Float: u8 = 4;
pub const JVM_CONSTANT_Long: u8 = 5;
pub const JVM_CONSTANT_Double: u8 = 6;
pub const JVM_CONSTANT_Class: u8 = 7;
pub const JVM_CONSTANT_String: u8 = 8;
pub const JVM_CONSTANT_Fieldref: u8 = 9;
pub const JVM_CONSTANT_Methodref: u8 = 10;
pub const JVM_CONSTANT_InterfaceMethodref: u8 = 11;
pub const JVM_CONSTANT_NameAndType: u8 = 12;
pub const JVM_CONSTANT_MethodHandle: u8 = 15;
pub const JVM_CONSTANT_MethodType: u8 = 16;
pub const JVM_CONSTANT_Dynamic: u8 = 17;
pub const JVM_CONSTANT_InvokeDynamic: u8 = 18;
pub const JVM_CONSTANT_Module: u8 = 19;
pub const JVM_CONSTANT_Package: u8 = 20;
pub const JVM_CONSTANT_ExternalMax: u8 = 20;

pub const JVM_REF_getField: u8 = 1;
pub const JVM_REF_getStatic: u8 = 2;
pub const JVM_REF_putField: u8 = 3;
pub const JVM_REF_putStatic: u8 = 4;
pub const JVM_REF_invokeVirtual: u8 = 5;
pub const JVM_REF_invokeStatic: u8 = 6;
pub const JVM_REF_invokeSpecial: u8 = 7;
pub const JVM_REF_newInvokeSpecial: u8 = 8;
pub const JVM_REF_invokeInterface: u8 = 9;

pub const JVM_ITEM_Top: u8 = 0;
pub const JVM_ITEM_Integer: u8 = 1;
pub const JVM_ITEM_Float: u8 = 2;
pub const JVM_ITEM_Double: u8 = 3;
pub const JVM_ITEM_Long: u8 = 4;
pub const JVM_ITEM_Null: u8 = 5;
pub const JVM_ITEM_UninitializedThis: u8 = 6;
pub const JVM_ITEM_Object: u8 = 7;
pub const JVM_ITEM_Uninitialized: u8 = 8;

pub const JVM_SIGNATURE_SLASH: u8 = 47;
pub const JVM_SIGNATURE_DOT: u8 = 46;
pub const JVM_SIGNATURE_SPECIAL: u8 = 60;
pub const JVM_SIGNATURE_ENDSPECIAL: u8 = 62;
pub const JVM_SIGNATURE_ARRAY: u8 = 91;
pub const JVM_SIGNATURE_BYTE: u8 = 66;
pub const JVM_SIGNATURE_CHAR: u8 = 67;
pub const JVM_SIGNATURE_CLASS: u8 = 76;
pub const JVM_SIGNATURE_ENDCLASS: u8 = 59;
pub const JVM_SIGNATURE_ENUM: u8 = 69;
pub const JVM_SIGNATURE_FLOAT: u8 = 70;
pub const JVM_SIGNATURE_DOUBLE: u8 = 68;
pub const JVM_SIGNATURE_FUNC: u8 = 40;
pub const JVM_SIGNATURE_ENDFUNC: u8 = 41;
pub const JVM_SIGNATURE_INT: u8 = 73;
pub const JVM_SIGNATURE_LONG: u8 = 74;
pub const JVM_SIGNATURE_SHORT: u8 = 83;
pub const JVM_SIGNATURE_VOID: u8 = 86;
pub const JVM_SIGNATURE_BOOLEAN: u8 = 90;

pub const JVM_OPC_nop: u8 = 0;
pub const JVM_OPC_aconst_null: u8 = 1;
pub const JVM_OPC_iconst_m1: u8 = 2;
pub const JVM_OPC_iconst_0: u8 = 3;
pub const JVM_OPC_iconst_1: u8 = 4;
pub const JVM_OPC_iconst_2: u8 = 5;
pub const JVM_OPC_iconst_3: u8 = 6;
pub const JVM_OPC_iconst_4: u8 = 7;
pub const JVM_OPC_iconst_5: u8 = 8;
pub const JVM_OPC_lconst_0: u8 = 9;
pub const JVM_OPC_lconst_1: u8 = 10;
pub const JVM_OPC_fconst_0: u8 = 11;
pub const JVM_OPC_fconst_1: u8 = 12;
pub const JVM_OPC_fconst_2: u8 = 13;
pub const JVM_OPC_dconst_0: u8 = 14;
pub const JVM_OPC_dconst_1: u8 = 15;
pub const JVM_OPC_bipush: u8 = 16;
pub const JVM_OPC_sipush: u8 = 17;
pub const JVM_OPC_ldc: u8 = 18;
pub const JVM_OPC_ldc_w: u8 = 19;
pub const JVM_OPC_ldc2_w: u8 = 20;
pub const JVM_OPC_iload: u8 = 21;
pub const JVM_OPC_lload: u8 = 22;
pub const JVM_OPC_fload: u8 = 23;
pub const JVM_OPC_dload: u8 = 24;
pub const JVM_OPC_aload: u8 = 25;
pub const JVM_OPC_iload_0: u8 = 26;
pub const JVM_OPC_iload_1: u8 = 27;
pub const JVM_OPC_iload_2: u8 = 28;
pub const JVM_OPC_iload_3: u8 = 29;
pub const JVM_OPC_lload_0: u8 = 30;
pub const JVM_OPC_lload_1: u8 = 31;
pub const JVM_OPC_lload_2: u8 = 32;
pub const JVM_OPC_lload_3: u8 = 33;
pub const JVM_OPC_fload_0: u8 = 34;
pub const JVM_OPC_fload_1: u8 = 35;
pub const JVM_OPC_fload_2: u8 = 36;
pub const JVM_OPC_fload_3: u8 = 37;
pub const JVM_OPC_dload_0: u8 = 38;
pub const JVM_OPC_dload_1: u8 = 39;
pub const JVM_OPC_dload_2: u8 = 40;
pub const JVM_OPC_dload_3: u8 = 41;
pub const JVM_OPC_aload_0: u8 = 42;
pub const JVM_OPC_aload_1: u8 = 43;
pub const JVM_OPC_aload_2: u8 = 44;
pub const JVM_OPC_aload_3: u8 = 45;
pub const JVM_OPC_iaload: u8 = 46;
pub const JVM_OPC_laload: u8 = 47;
pub const JVM_OPC_faload: u8 = 48;
pub const JVM_OPC_daload: u8 = 49;
pub const JVM_OPC_aaload: u8 = 50;
pub const JVM_OPC_baload: u8 = 51;
pub const JVM_OPC_caload: u8 = 52;
pub const JVM_OPC_saload: u8 = 53;
pub const JVM_OPC_istore: u8 = 54;
pub const JVM_OPC_lstore: u8 = 55;
pub const JVM_OPC_fstore: u8 = 56;
pub const JVM_OPC_dstore: u8 = 57;
pub const JVM_OPC_astore: u8 = 58;
pub const JVM_OPC_istore_0: u8 = 59;
pub const JVM_OPC_istore_1: u8 = 60;
pub const JVM_OPC_istore_2: u8 = 61;
pub const JVM_OPC_istore_3: u8 = 62;
pub const JVM_OPC_lstore_0: u8 = 63;
pub const JVM_OPC_lstore_1: u8 = 64;
pub const JVM_OPC_lstore_2: u8 = 65;
pub const JVM_OPC_lstore_3: u8 = 66;
pub const JVM_OPC_fstore_0: u8 = 67;
pub const JVM_OPC_fstore_1: u8 = 68;
pub const JVM_OPC_fstore_2: u8 = 69;
pub const JVM_OPC_fstore_3: u8 = 70;
pub const JVM_OPC_dstore_0: u8 = 71;
pub const JVM_OPC_dstore_1: u8 = 72;
pub const JVM_OPC_dstore_2: u8 = 73;
pub const JVM_OPC_dstore_3: u8 = 74;
pub const JVM_OPC_astore_0: u8 = 75;
pub const JVM_OPC_astore_1: u8 = 76;
pub const JVM_OPC_astore_2: u8 = 77;
pub const JVM_OPC_astore_3: u8 = 78;
pub const JVM_OPC_iastore: u8 = 79;
pub const JVM_OPC_lastore: u8 = 80;
pub const JVM_OPC_fastore: u8 = 81;
pub const JVM_OPC_dastore: u8 = 82;
pub const JVM_OPC_aastore: u8 = 83;
pub const JVM_OPC_bastore: u8 = 84;
pub const JVM_OPC_castore: u8 = 85;
pub const JVM_OPC_sastore: u8 = 86;
pub const JVM_OPC_pop: u8 = 87;
pub const JVM_OPC_pop2: u8 = 88;
pub const JVM_OPC_dup: u8 = 89;
pub const JVM_OPC_dup_x1: u8 = 90;
pub const JVM_OPC_dup_x2: u8 = 91;
pub const JVM_OPC_dup2: u8 = 92;
pub const JVM_OPC_dup2_x1: u8 = 93;
pub const JVM_OPC_dup2_x2: u8 = 94;
pub const JVM_OPC_swap: u8 = 95;
pub const JVM_OPC_iadd: u8 = 96;
pub const JVM_OPC_ladd: u8 = 97;
pub const JVM_OPC_fadd: u8 = 98;
pub const JVM_OPC_dadd: u8 = 99;
pub const JVM_OPC_isub: u8 = 100;
pub const JVM_OPC_lsub: u8 = 101;
pub const JVM_OPC_fsub: u8 = 102;
pub const JVM_OPC_dsub: u8 = 103;
pub const JVM_OPC_imul: u8 = 104;
pub const JVM_OPC_lmul: u8 = 105;
pub const JVM_OPC_fmul: u8 = 106;
pub const JVM_OPC_dmul: u8 = 107;
pub const JVM_OPC_idiv: u8 = 108;
pub const JVM_OPC_ldiv: u8 = 109;
pub const JVM_OPC_fdiv: u8 = 110;
pub const JVM_OPC_ddiv: u8 = 111;
pub const JVM_OPC_irem: u8 = 112;
pub const JVM_OPC_lrem: u8 = 113;
pub const JVM_OPC_frem: u8 = 114;
pub const JVM_OPC_drem: u8 = 115;
pub const JVM_OPC_ineg: u8 = 116;
pub const JVM_OPC_lneg: u8 = 117;
pub const JVM_OPC_fneg: u8 = 118;
pub const JVM_OPC_dneg: u8 = 119;
pub const JVM_OPC_ishl: u8 = 120;
pub const JVM_OPC_lshl: u8 = 121;
pub const JVM_OPC_ishr: u8 = 122;
pub const JVM_OPC_lshr: u8 = 123;
pub const JVM_OPC_iushr: u8 = 124;
pub const JVM_OPC_lushr: u8 = 125;
pub const JVM_OPC_iand: u8 = 126;
pub const JVM_OPC_land: u8 = 127;
pub const JVM_OPC_ior: u8 = 128;
pub const JVM_OPC_lor: u8 = 129;
pub const JVM_OPC_ixor: u8 = 130;
pub const JVM_OPC_lxor: u8 = 131;
pub const JVM_OPC_iinc: u8 = 132;
pub const JVM_OPC_i2l: u8 = 133;
pub const JVM_OPC_i2f: u8 = 134;
pub const JVM_OPC_i2d: u8 = 135;
pub const JVM_OPC_l2i: u8 = 136;
pub const JVM_OPC_l2f: u8 = 137;
pub const JVM_OPC_l2d: u8 = 138;
pub const JVM_OPC_f2i: u8 = 139;
pub const JVM_OPC_f2l: u8 = 140;
pub const JVM_OPC_f2d: u8 = 141;
pub const JVM_OPC_d2i: u8 = 142;
pub const JVM_OPC_d2l: u8 = 143;
pub const JVM_OPC_d2f: u8 = 144;
pub const JVM_OPC_i2b: u8 = 145;
pub const JVM_OPC_i2c: u8 = 146;
pub const JVM_OPC_i2s: u8 = 147;
pub const JVM_OPC_lcmp: u8 = 148;
pub const JVM_OPC_fcmpl: u8 = 149;
pub const JVM_OPC_fcmpg: u8 = 150;
pub const JVM_OPC_dcmpl: u8 = 151;
pub const JVM_OPC_dcmpg: u8 = 152;
pub const JVM_OPC_ifeq: u8 = 153;
pub const JVM_OPC_ifne: u8 = 154;
pub const JVM_OPC_iflt: u8 = 155;
pub const JVM_OPC_ifge: u8 = 156;
pub const JVM_OPC_ifgt: u8 = 157;
pub const JVM_OPC_ifle: u8 = 158;
pub const JVM_OPC_if_icmpeq: u8 = 159;
pub const JVM_OPC_if_icmpne: u8 = 160;
pub const JVM_OPC_if_icmplt: u8 = 161;
pub const JVM_OPC_if_icmpge: u8 = 162;
pub const JVM_OPC_if_icmpgt: u8 = 163;
pub const JVM_OPC_if_icmple: u8 = 164;
pub const JVM_OPC_if_acmpeq: u8 = 165;
pub const JVM_OPC_if_acmpne: u8 = 166;
pub const JVM_OPC_goto: u8 = 167;
pub const JVM_OPC_jsr: u8 = 168;
pub const JVM_OPC_ret: u8 = 169;
pub const JVM_OPC_tableswitch: u8 = 170;
pub const JVM_OPC_lookupswitch: u8 = 171;
pub const JVM_OPC_ireturn: u8 = 172;
pub const JVM_OPC_lreturn: u8 = 173;
pub const JVM_OPC_freturn: u8 = 174;
pub const JVM_OPC_dreturn: u8 = 175;
pub const JVM_OPC_areturn: u8 = 176;
pub const JVM_OPC_return: u8 = 177;
pub const JVM_OPC_getstatic: u8 = 178;
pub const JVM_OPC_putstatic: u8 = 179;
pub const JVM_OPC_getfield: u8 = 180;
pub const JVM_OPC_putfield: u8 = 181;
pub const JVM_OPC_invokevirtual: u8 = 182;
pub const JVM_OPC_invokespecial: u8 = 183;
pub const JVM_OPC_invokestatic: u8 = 184;
pub const JVM_OPC_invokeinterface: u8 = 185;
pub const JVM_OPC_invokedynamic: u8 = 186;
pub const JVM_OPC_new: u8 = 187;
pub const JVM_OPC_newarray: u8 = 188;
pub const JVM_OPC_anewarray: u8 = 189;
pub const JVM_OPC_arraylength: u8 = 190;
pub const JVM_OPC_athrow: u8 = 191;
pub const JVM_OPC_checkcast: u8 = 192;
pub const JVM_OPC_instanceof: u8 = 193;
pub const JVM_OPC_monitorenter: u8 = 194;
pub const JVM_OPC_monitorexit: u8 = 195;
pub const JVM_OPC_wide: u8 = 196;
pub const JVM_OPC_multianewarray: u8 = 197;
pub const JVM_OPC_ifnull: u8 = 198;
pub const JVM_OPC_ifnonnull: u8 = 199;
pub const JVM_OPC_goto_w: u8 = 200;
pub const JVM_OPC_jsr_w: u8 = 201;
pub const JVM_OPC_MAX: u8 = 201;
